weathereye/__init__.py
weathereye/cli.py
weathereye/weathereye.py
weathereye-0.1.0.dist-info/AUTHORS.rst
weathereye-0.1.0.dist-info/LICENSE
weathereye-0.1.0.dist-info/METADATA
weathereye-0.1.0.dist-info/WHEEL
weathereye-0.1.0.dist-info/entry_points.txt
weathereye-0.1.0.dist-info/top_level.txt
weathereye-0.1.0.dist-info/RECORD
