Metadata-Version: 2.1
Name: weathereye
Version: 0.1.0
Summary: WeatherEye Python Package and CLI
Home-page: https://github.com/isedwards/weathereye
Author: Ian Edwards
Author-email: ian@myacorn.com
License: MIT license
Keywords: weathereye
Classifier: Development Status :: 2 - Pre-Alpha
Classifier: Intended Audience :: Developers
Classifier: License :: OSI Approved :: MIT License
Classifier: Natural Language :: English
Classifier: Programming Language :: Python :: 3
Classifier: Programming Language :: Python :: 3.6
Classifier: Programming Language :: Python :: 3.7
Classifier: Programming Language :: Python :: 3.8
Requires-Python: >=3.6
License-File: LICENSE
License-File: AUTHORS.rst
Requires-Dist: Click >=7.0
